casebased/__init__.py
casebased/actors/__init__.py
casebased/actors/adapter.py
casebased/actors/retriever.py
casebased/case_base_adapter.py
casebased/components/__init__.py
casebased/components/casebase/__init__.py
casebased/components/casebase/casebase.py
casebased/components/casebase/data_source_adapter.py
casebased/components/casebase/query_case.py
casebased/components/similarity_measure/__init__.py
casebased/components/similarity_measure/functions/__init__.py
casebased/components/similarity_measure/functions/generic.py
casebased/components/similarity_measure/functions/numerical.py
casebased/components/similarity_measure/functions/strings.py
casebased/components/similarity_measure/schema.py
casebased/components/similarity_measure/types.py
casebased/components/similarity_measure/weight.py
casebased/components/vocabulary/__init__.py
casebased/components/vocabulary/attribute.py
casebased/components/vocabulary/case.py
casebased/components/vocabulary/conditions.py
casebased/components/vocabulary/parser.py
casebased/components/vocabulary/vocabulary.py
casebased/system.py
casebased/utils/__init__.py
casebased/utils/convert.py
casebased/utils/errors.py
casebased-0.1.6.dist-info/LICENSE
casebased-0.1.6.dist-info/METADATA
casebased-0.1.6.dist-info/WHEEL
casebased-0.1.6.dist-info/RECORD
