Metadata-Version: 2.3
Name: casebased
Version: 0.1.6
Summary: CaseBased is a python library that implements the priciples of case-based reasoning.
License: The MIT License (MIT)
Keywords: CBR,case-based reasoning,ML,Machine Learning
Author: Jonas Liendl
Author-email: casebased@gmail.com
Requires-Python: >=3.9, <4.0
Classifier: Development Status :: 3 - Alpha
Classifier: Intended Audience :: Developers
Classifier: Operating System :: OS Independent
Classifier: Topic :: Software Development :: Libraries :: Python Modules
Classifier: License :: OSI Approved :: MIT License
Classifier: Programming Language :: Python :: 3
Classifier: Programming Language :: Python :: 3.9
Project-URL: Homepage, https://www.casebased.org/
Project-URL: Repository, https://github.com/Case-Based/casebased
